pyawsbuckets
