Metadata-Version: 1.1
Name: pyawsbuckets
Version: 1.2.0
Summary: Handle Amazon S3 PUT/GET/DELETE/sign interactions
Home-page: http://pypi.python.org/pypi/pyawsbuckets
Author: Mark Henwood
Author-email: mark@mcbh.co.uk
License: MIT
Keywords: amazon aws s3 buckets
Platform: UNKNOWN
Classifier: Development Status :: 5 - Production/Stable
Classifier: Environment :: Plugins
Classifier: Intended Audience :: Developers
Classifier: License :: OSI Approved :: MIT License
Classifier: Natural Language :: English
Classifier: Operating System :: OS Independent
Classifier: Programming Language :: Python :: 2.7
Classifier: Topic :: Utilities
Requires: httplib2
Provides: pyawsbuckets
